appAuto/__init__.py
appAuto/main.py
appAuto/common/__init__.py
appAuto/common/imagesCache.py
appAuto/common/singleton.py
appAuto/internals/__init__.py
appAuto/internals/keyboard.py
appAuto/internals/mouse.py
appAuto/internals/ocr.py
appAuto/internals/screenShot.py
appAuto/internals/paddle/__init__.py
appAuto/internals/paddle/paddleOCR.py
appAuto/models/__init__.py
appAuto/models/datetime.py
appAuto/models/screenItem.py
ai2soft.desktop.app.automation-0.0.3.dist-info/LICENSE
ai2soft.desktop.app.automation-0.0.3.dist-info/METADATA
ai2soft.desktop.app.automation-0.0.3.dist-info/WHEEL
ai2soft.desktop.app.automation-0.0.3.dist-info/top_level.txt
ai2soft.desktop.app.automation-0.0.3.dist-info/RECORD
