Metadata-Version: 2.1
Name: ai2soft.desktop.app.automation
Version: 0.0.3
Summary: 用于完与一些自动化的操作
Home-page: 
Author: ai2soft.cn
Author-email: goldli@live.cn
License: MIT
Classifier: Programming Language :: Python :: 3.10
License-File: LICENSE
